thieves/__init__.py
thieves/thieves.py
thieves-0.1.1.dist-info/LICENSE
thieves-0.1.1.dist-info/METADATA
thieves-0.1.1.dist-info/WHEEL
thieves-0.1.1.dist-info/top_level.txt
thieves-0.1.1.dist-info/RECORD
